{
  "trace": [
    {
      "step": "1",
      "stack": "0",
      "input": "( num + id ) / num $",
      "action": "s1"
    },
    {
      "step": "2",
      "stack": "0 ( 1",
      "input": "num + id ) / num $",
      "action": "s14"
    },
    {
      "step": "3",
      "stack": "0 ( 1 num 14",
      "input": "+ id ) / num $",
      "action": "r9"
    },
    {
      "step": "4",
      "stack": "0 ( 1 G 10",
      "input": "+ id ) / num $",
      "action": "r7"
    },
    {
      "step": "5",
      "stack": "0 ( 1 F 9",
      "input": "+ id ) / num $",
      "action": "r6"
    },
    {
      "step": "6",
      "stack": "0 ( 1 T 12",
      "input": "+ id ) / num $",
      "action": "r3"
    },
    {
      "step": "7",
      "stack": "0 ( 1 S 11",
      "input": "+ id ) / num $",
      "action": "s21"
    },
    {
      "step": "8",
      "stack": "0 ( 1 S 11 + 21",
      "input": "id ) / num $",
      "action": "s13"
    },
    {
      "step": "9",
      "stack": "0 ( 1 S 11 + 21 id 13",
      "input": ") / num $",
      "action": "r10"
    },
    {
      "step": "10",
      "stack": "0 ( 1 S 11 + 21 G 10",
      "input": ") / num $",
      "action": "r7"
    },
    {
      "step": "11",
      "stack": "0 ( 1 S 11 + 21 F 9",
      "input": ") / num $",
      "action": "r6"
    },
    {
      "step": "12",
      "stack": "0 ( 1 S 11 + 21 T 30",
      "input": ") / num $",
      "action": "r1"
    },
    {
      "step": "13",
      "stack": "0 ( 1 S 11",
      "input": ") / num $",
      "action": "s20"
    },
    {
      "step": "14",
      "stack": "0 ( 1 S 11 ) 20",
      "input": "/ num $",
      "action": "r8"
    },
    {
      "step": "15",
      "stack": "0 G 3",
      "input": "/ num $",
      "action": "r7"
    },
    {
      "step": "16",
      "stack": "0 F 2",
      "input": "/ num $",
      "action": "r6"
    },
    {
      "step": "17",
      "stack": "0 T 5",
      "input": "/ num $",
      "action": "s18"
    },
    {
      "step": "18",
      "stack": "0 T 5 / 18",
      "input": "num $",
      "action": "s7"
    },
    {
      "step": "19",
      "stack": "0 T 5 / 18 num 7",
      "input": "$",
      "action": "r9"
    },
    {
      "step": "20",
      "stack": "0 T 5 / 18 G 3",
      "input": "$",
      "action": "r7"
    },
    {
      "step": "21",
      "stack": "0 T 5 / 18 F 28",
      "input": "$",
      "action": "r5"
    },
    {
      "step": "22",
      "stack": "0 T 5",
      "input": "$",
      "action": "r3"
    },
    {
      "step": "23",
      "stack": "0 S 4",
      "input": "$",
      "action": "acc"
    }
  ]
}
